dbinfer_bench/__init__.py
dbinfer_bench/dataset_meta.py
dbinfer_bench/download.py
dbinfer_bench/download_config.yaml
dbinfer_bench/graph_dataset.py
dbinfer_bench/ondisk_dataset_creator.py
dbinfer_bench/rdb_dataset.py
dbinfer_bench/table_loader.py
dbinfer_bench/table_writer.py
dbinfer_bench/version.py
dbinfer_bench/yaml_utils.py
dbinfer_bench-0.1.dist-info/LICENSE
dbinfer_bench-0.1.dist-info/METADATA
dbinfer_bench-0.1.dist-info/NOTICE
dbinfer_bench-0.1.dist-info/WHEEL
dbinfer_bench-0.1.dist-info/top_level.txt
dbinfer_bench-0.1.dist-info/RECORD
