Metadata-Version: 2.1
Name: dbinfer-bench
Version: 0.1
Home-page: https://github.com/awslabs/multi-table-benchmark
Author: AWS Shanghai AI Lab
License: APACHE
Requires-Python: >=3.7
License-File: LICENSE
License-File: NOTICE
Requires-Dist: pydantic
Requires-Dist: numpy
Requires-Dist: pandas
Requires-Dist: boto3
Requires-Dist: requests[security]
Requires-Dist: pyyaml
Requires-Dist: dgl >=2.1a240205
Requires-Dist: sqlalchemy
